setup.py
spell_messenger_server/__init__.py
spell_messenger_server/__main__.py
spell_messenger_server/main.py
spell_messenger_server.egg-info/PKG-INFO
spell_messenger_server.egg-info/SOURCES.txt
spell_messenger_server.egg-info/dependency_links.txt
spell_messenger_server.egg-info/entry_points.txt
spell_messenger_server.egg-info/not-zip-safe
spell_messenger_server.egg-info/requires.txt
spell_messenger_server.egg-info/top_level.txt
spell_messenger_server/jim/__init__.py
spell_messenger_server/jim/config.py
spell_messenger_server/jim/utils.py
spell_messenger_server/server/__init__.py
spell_messenger_server/server/decorators.py
spell_messenger_server/server/descriptors.py
spell_messenger_server/server/handlers.py
spell_messenger_server/server/metaclasses.py
spell_messenger_server/server/server.py
spell_messenger_server/server/server_gui.py
spell_messenger_server/server/settings.py
spell_messenger_server/server/db/__init__.py
spell_messenger_server/server/db/models.py
spell_messenger_server/server/db/repository.py
spell_messenger_server/server/log/__init__.py
spell_messenger_server/server/log/config.py