Metadata-Version: 1.0
Name: spell-messenger-server
Version: 4.0
Summary: Spell messenger - Server package
Home-page: https://github.com/SPELLGIRL/PyQT
Author: Antonina Kletskina
Author-email: chepushilka@yandex.ru
License: UNKNOWN
Platform: UNKNOWN
